{
  "project_info": {
    "project_number": "180944097442",
    "project_id": "dairy-harbor-mobile",
    "storage_bucket": "dairy-harbor-mobile.appspot.com"
  },
  "client": [
    {
      "client_info": {
        "mobilesdk_app_id": "1:180944097442:android:5444a9ec0636b3c7e407fb",
        "android_client_info": {
          "package_name": "com.example.dairy_harbor"
        }
      },
      "oauth_client": [],
      "api_key": [
        {
          "current_key": "AIzaSyABxoAiXruglakT_sz-cn8yBFYOyR86Q-s"
        }
      ],
      "services": {
        "appinvite_service": {
          "other_platform_oauth_client": []
        }
      }
    }
  ],
  "configuration_version": "1"
}